blax/__init__.py
blax-0.1.0.dist-info/METADATA
blax-0.1.0.dist-info/WHEEL
blax-0.1.0.dist-info/RECORD
