Metadata-Version: 2.1
Name: blax
Version: 0.1.0
Summary: Just like Black for Python but nicer!
License: apache
Author: lamnguyenx
Requires-Python: >=3.10,<4.0
Classifier: License :: Other/Proprietary License
Classifier: Programming Language :: Python :: 3
Classifier: Programming Language :: Python :: 3.10
Classifier: Programming Language :: Python :: 3.11
Classifier: Programming Language :: Python :: 3.12
